<?xml version="1.0" ?>

<container xmlns="http://symfony.com/schema/dic/services"
           xmlns:xsi="http://www.w3.org/2001/XMLSchema-instance"
           xsi:schemaLocation="http://symfony.com/schema/dic/services http://symfony.com/schema/dic/services/services-1.0.xsd">

    <parameters>
        <parameter key="inviqa_launchdarkly.feature_requester.class">LaunchDarkly\GuzzleFeatureRequester</parameter>
    </parameters>

    <services>

        <service id="inviqa_launchdarkly.inner_client" class="LaunchDarkly\LDClient">
            <argument>%inviqa_launchdarkly.feature_requester.api_key%</argument>
            <argument>%inviqa_launchdarkly.feature_requester.options%</argument>
        </service>

        <service id="inviqa_launchdarkly.user_providing_client" class="Inviqa\LaunchDarklyBundle\Client\UserProvidingClient">
            <argument type="service" id="inviqa_launchdarkly.inner_client"/>
            <argument type="service" id="inviqa_launchdarkly.key_provider"/>
            <argument type="service" id="inviqa_launchdarkly.user_factory"/>
        </service>

        <service id="inviqa_launchdarkly.client" alias="inviqa_launchdarkly.user_providing_client"/>

        <service id="inviqa_launchdarkly.no_context_client" alias="inviqa_launchdarkly.user_providing_client"/>

        <service id="inviqa_launchdarkly.session_key_provider" class="Inviqa\LaunchDarklyBundle\User\SessionKeyProvider">
            <argument type="service" id="request_stack"/>
        </service>

        <service id="inviqa_launchdarkly.simple_user_factory" class="Inviqa\LaunchDarklyBundle\User\SimpleUserFactory"/>

        <service id="inviqa_launchdarkly.twig_extension"
                 class="Inviqa\LaunchDarklyBundle\Twig\FlagExtension"
                 public="false">
            <argument type="service" id="inviqa_launchdarkly.no_context_client"/>
            <tag name="twig.extension" />
        </service>

        <service id="inviqa_launchdarkly.service_toggler"
                 class="Inviqa\LaunchDarklyBundle\DependencyInjection\ServiceToggler"
                 >
        </service>

    </services>

</container>
